blueair_api/__init__.py
blueair_api/callbacks.py
blueair_api/const.py
blueair_api/device.py
blueair_api/device_aws.py
blueair_api/errors.py
blueair_api/http_aws_blueair.py
blueair_api/http_blueair.py
blueair_api/intermediate_representation_aws.py
blueair_api/model_enum.py
blueair_api/stub.py
blueair_api/util.py
blueair_api/util_bootstrap.py
blueair_api/util_http.py
blueair_api-1.44.0.dist-info/licenses/LICENSE
blueair_api-1.44.0.dist-info/METADATA
blueair_api-1.44.0.dist-info/WHEEL
blueair_api-1.44.0.dist-info/top_level.txt
blueair_api-1.44.0.dist-info/RECORD
